docs/AApi.md
docs/AboutApi.md
docs/Action.md
docs/ActivitiesApi.md
docs/Activity.md
docs/Alert.md
docs/AlertsApi.md
docs/ArchInfo.md
docs/AvailableAction.md
docs/Batch.md
docs/BatchesApi.md
docs/BlobInfo.md
docs/Blueprint.md
docs/BlueprintsApi.md
docs/BootEnv.md
docs/BootEnvsApi.md
docs/CatalogItem.md
docs/CatalogItemsApi.md
docs/Cert.md
docs/Claim.md
docs/Classifier.md
docs/Cluster.md
docs/ClusterState.md
docs/ClustersApi.md
docs/Connection.md
docs/ConnectionApi.md
docs/ConnectionsApi.md
docs/Content.md
docs/ContentMetaData.md
docs/ContentSummary.md
docs/ContentsApi.md
docs/Context.md
docs/ContextsApi.md
docs/DhcpOption.md
docs/Element.md
docs/ElementAction.md
docs/Endpoint.md
docs/EndpointsApi.md
docs/Error.md
docs/Event.md
docs/EventsApi.md
docs/FileData.md
docs/FilePaths.md
docs/FilesApi.md
docs/Filter.md
docs/FiltersApi.md
docs/HaPassiveState.md
docs/IdentityProvider.md
docs/IdentityProvidersApi.md
docs/Index.md
docs/IndexesApi.md
docs/Info.md
docs/InfoApi.md
docs/Interface.md
docs/InterfacesApi.md
docs/IsoPaths.md
docs/IsosApi.md
docs/Job.md
docs/JobAction.md
docs/JobActions.md
docs/JobsApi.md
docs/Lease.md
docs/LeasesApi.md
docs/Level.md
docs/License.md
docs/LicenseBundle.md
docs/Line.md
docs/LogsApi.md
docs/Machine.md
docs/MachineFingerprint.md
docs/MachinesApi.md
docs/MemoryId.md
docs/MenuGroup.md
docs/MenuItem.md
docs/Meta.md
docs/MetaApi.md
docs/NodeInfo.md
docs/ObjectPrefixes.md
docs/ObjectsApi.md
docs/Operation.md
docs/OsInfo.md
docs/Param.md
docs/ParamsApi.md
docs/Patch.md
docs/Plugin.md
docs/PluginProvider.md
docs/PluginProviderUploadInfo.md
docs/PluginProvidersApi.md
docs/PluginsApi.md
docs/Pool.md
docs/PoolAutoFill.md
docs/PoolResult.md
docs/PoolStatus.md
docs/PoolTransitionActions.md
docs/PoolsApi.md
docs/PrefsApi.md
docs/PrivateKey.md
docs/Profile.md
docs/ProfilesApi.md
docs/Query.md
docs/Reservation.md
docs/ReservationsApi.md
docs/ResourceBroker.md
docs/ResourceBrokersApi.md
docs/Role.md
docs/RolesApi.md
docs/Section.md
docs/Sections.md
drppy_client-4.15.3.dist-info/METADATA
drppy_client-4.15.3.dist-info/WHEEL
drppy_client-4.15.3.dist-info/top_level.txt
drppy_client-4.15.3.dist-info/RECORD
