Metadata-Version: 2.4
Name: drppy_client
Version: 4.15.3
Summary: Python Library to interact with the digitalrebar API.
Home-page: https://gitlab.com/rackn/drppy_client
Author-email: RackN Engineering <eng@rackn.com>
Project-URL: Homepage, https://gitlab.com/rackn/drppy_client
Project-URL: Issues, https://gitlab.com/rackn/drppy_client
Classifier: Programming Language :: Python :: 3
Classifier: License :: OSI Approved :: Apache Software License
Classifier: Operating System :: OS Independent
Requires-Python: >=3.5
Requires-Dist: certifi>=14.05.14
Requires-Dist: six>=1.10
Requires-Dist: python-dateutil>=2.5.3
Requires-Dist: urllib3>=1.15.1
Requires-Dist: click>=8.1.7
Requires-Dist: pynacl>=1.5
Dynamic: home-page
